{
	"textures": [
		{
			"image": "newrole",
			"format": "RGBA8888",
			"size": {
				"w": 70,
				"h": 355
			},
			"scale": 1,
			"frames": [
				{
					"filename": "people_panel bg_left",
					"rotated": false,
					"trimmed": false,
					"sourceSize": {
						"w": 30,
						"h": 265
					},
					"spriteSourceSize": {
						"x": 0,
						"y": 0,
						"w": 30,
						"h": 265
					},
					"frame": {
						"x": 1,
						"y": 1,
						"w": 30,
						"h": 265
					}
				},
				{
					"filename": "people_man",
					"rotated": false,
					"trimmed": true,
					"sourceSize": {
						"w": 38,
						"h": 38
					},
					"spriteSourceSize": {
						"x": 1,
						"y": 1,
						"w": 36,
						"h": 36
					},
					"frame": {
						"x": 1,
						"y": 268,
						"w": 36,
						"h": 36
					}
				},
				{
					"filename": "people_panel bg_right",
					"rotated": false,
					"trimmed": false,
					"sourceSize": {
						"w": 30,
						"h": 265
					},
					"spriteSourceSize": {
						"x": 0,
						"y": 0,
						"w": 30,
						"h": 265
					},
					"frame": {
						"x": 33,
						"y": 1,
						"w": 30,
						"h": 265
					}
				},
				{
					"filename": "people_woman",
					"rotated": false,
					"trimmed": true,
					"sourceSize": {
						"w": 38,
						"h": 38
					},
					"spriteSourceSize": {
						"x": 1,
						"y": 1,
						"w": 36,
						"h": 36
					},
					"frame": {
						"x": 1,
						"y": 306,
						"w": 36,
						"h": 36
					}
				},
				{
					"filename": "people_more",
					"rotated": false,
					"trimmed": false,
					"sourceSize": {
						"w": 44,
						"h": 10
					},
					"spriteSourceSize": {
						"x": 0,
						"y": 0,
						"w": 44,
						"h": 10
					},
					"frame": {
						"x": 1,
						"y": 344,
						"w": 44,
						"h": 10
					}
				},
				{
					"filename": "people_panel bg_middle",
					"rotated": false,
					"trimmed": false,
					"sourceSize": {
						"w": 4,
						"h": 265
					},
					"spriteSourceSize": {
						"x": 0,
						"y": 0,
						"w": 4,
						"h": 265
					},
					"frame": {
						"x": 65,
						"y": 1,
						"w": 4,
						"h": 265
					}
				}
			]
		}
	],
	"meta": {
		"app": "https://www.codeandweb.com/texturepacker",
		"version": "3.0",
		"smartupdate": "$TexturePacker:SmartUpdate:45ef8c4a3d965966c57f43579e4dfd34:298cd4491439cb7feec5e0164258b28d:db8727d1d217dd298548cc3b7f5e45be$"
	}
}
