{
  "1": {
    "type": "sprite",
    "text": {
      "en": "",
      "zh": ""
    },
    "image": {
      "img": "frame",
      "animation": {
        "anikey": "frame_wrench",
        "frame": "1,2,3,4",
        "duration": 1200,
        "repeat": -1
      },
      "display": {
        "texturepath": "repair_furniture/repair_furniture.png",
        "datapath": "repair_furniture/repair_furniture.json"
      }
    }
  },
  "2": {
    "type": "sprite",
    "text": {
      "en": "",
      "zh": ""
    },
    "image": {
      "img": "tips",
      "animation": {
        "anikey": "frame_excla",
        "frame": "1,2,3,4",
        "duration": 1200,
        "repeat": -1
      },
      "display": {
        "texturepath": "repair_furniture/repair_furniture.png",
        "datapath": "repair_furniture/repair_furniture.json"
      }
    }
  }
}