{
	"textures": [
		{
			"image": "stareffect",
			"format": "RGBA8888",
			"size": {
				"w": 958,
				"h": 3201
			},
			"scale": 1,
			"frames": [
				{
					"filename": "star10",
					"rotated": false,
					"trimmed": true,
					"sourceSize": {
						"w": 583,
						"h": 570
					},
					"spriteSourceSize": {
						"x": 38,
						"y": 55,
						"w": 477,
						"h": 428
					},
					"frame": {
						"x": 1,
						"y": 1,
						"w": 477,
						"h": 428
					}
				},
				{
					"filename": "star11",
					"rotated": false,
					"trimmed": true,
					"sourceSize": {
						"w": 583,
						"h": 570
					},
					"spriteSourceSize": {
						"x": 38,
						"y": 55,
						"w": 477,
						"h": 428
					},
					"frame": {
						"x": 480,
						"y": 1,
						"w": 477,
						"h": 428
					}
				},
				{
					"filename": "star13",
					"rotated": false,
					"trimmed": true,
					"sourceSize": {
						"w": 583,
						"h": 570
					},
					"spriteSourceSize": {
						"x": 38,
						"y": 55,
						"w": 477,
						"h": 428
					},
					"frame": {
						"x": 1,
						"y": 431,
						"w": 477,
						"h": 428
					}
				},
				{
					"filename": "star15",
					"rotated": false,
					"trimmed": true,
					"sourceSize": {
						"w": 583,
						"h": 570
					},
					"spriteSourceSize": {
						"x": 38,
						"y": 55,
						"w": 477,
						"h": 428
					},
					"frame": {
						"x": 480,
						"y": 431,
						"w": 477,
						"h": 428
					}
				},
				{
					"filename": "star16",
					"rotated": false,
					"trimmed": true,
					"sourceSize": {
						"w": 583,
						"h": 570
					},
					"spriteSourceSize": {
						"x": 38,
						"y": 55,
						"w": 477,
						"h": 428
					},
					"frame": {
						"x": 1,
						"y": 861,
						"w": 477,
						"h": 428
					}
				},
				{
					"filename": "star17",
					"rotated": false,
					"trimmed": true,
					"sourceSize": {
						"w": 583,
						"h": 570
					},
					"spriteSourceSize": {
						"x": 38,
						"y": 55,
						"w": 477,
						"h": 428
					},
					"frame": {
						"x": 480,
						"y": 861,
						"w": 477,
						"h": 428
					}
				},
				{
					"filename": "star18",
					"rotated": false,
					"trimmed": true,
					"sourceSize": {
						"w": 583,
						"h": 570
					},
					"spriteSourceSize": {
						"x": 38,
						"y": 55,
						"w": 477,
						"h": 428
					},
					"frame": {
						"x": 1,
						"y": 1291,
						"w": 477,
						"h": 428
					}
				},
				{
					"filename": "star7",
					"rotated": false,
					"trimmed": true,
					"sourceSize": {
						"w": 583,
						"h": 570
					},
					"spriteSourceSize": {
						"x": 38,
						"y": 55,
						"w": 477,
						"h": 428
					},
					"frame": {
						"x": 480,
						"y": 1291,
						"w": 477,
						"h": 428
					}
				},
				{
					"filename": "star8",
					"rotated": false,
					"trimmed": true,
					"sourceSize": {
						"w": 583,
						"h": 570
					},
					"spriteSourceSize": {
						"x": 38,
						"y": 55,
						"w": 477,
						"h": 428
					},
					"frame": {
						"x": 1,
						"y": 1721,
						"w": 477,
						"h": 428
					}
				},
				{
					"filename": "star9",
					"rotated": false,
					"trimmed": true,
					"sourceSize": {
						"w": 583,
						"h": 570
					},
					"spriteSourceSize": {
						"x": 38,
						"y": 55,
						"w": 477,
						"h": 428
					},
					"frame": {
						"x": 480,
						"y": 1721,
						"w": 477,
						"h": 428
					}
				},
				{
					"filename": "star14",
					"rotated": false,
					"trimmed": true,
					"sourceSize": {
						"w": 583,
						"h": 570
					},
					"spriteSourceSize": {
						"x": 38,
						"y": 67,
						"w": 477,
						"h": 416
					},
					"frame": {
						"x": 1,
						"y": 2151,
						"w": 477,
						"h": 416
					}
				},
				{
					"filename": "star6",
					"rotated": false,
					"trimmed": true,
					"sourceSize": {
						"w": 583,
						"h": 570
					},
					"spriteSourceSize": {
						"x": 38,
						"y": 55,
						"w": 477,
						"h": 396
					},
					"frame": {
						"x": 480,
						"y": 2151,
						"w": 477,
						"h": 396
					}
				},
				{
					"filename": "star12",
					"rotated": false,
					"trimmed": true,
					"sourceSize": {
						"w": 583,
						"h": 570
					},
					"spriteSourceSize": {
						"x": 52,
						"y": 55,
						"w": 463,
						"h": 428
					},
					"frame": {
						"x": 1,
						"y": 2569,
						"w": 463,
						"h": 428
					}
				},
				{
					"filename": "star5",
					"rotated": false,
					"trimmed": true,
					"sourceSize": {
						"w": 583,
						"h": 570
					},
					"spriteSourceSize": {
						"x": 149,
						"y": 94,
						"w": 366,
						"h": 357
					},
					"frame": {
						"x": 480,
						"y": 2549,
						"w": 366,
						"h": 357
					}
				},
				{
					"filename": "star4",
					"rotated": false,
					"trimmed": true,
					"sourceSize": {
						"w": 583,
						"h": 570
					},
					"spriteSourceSize": {
						"x": 149,
						"y": 148,
						"w": 246,
						"h": 292
					},
					"frame": {
						"x": 466,
						"y": 2908,
						"w": 246,
						"h": 292
					}
				},
				{
					"filename": "star3",
					"rotated": false,
					"trimmed": true,
					"sourceSize": {
						"w": 583,
						"h": 570
					},
					"spriteSourceSize": {
						"x": 149,
						"y": 174,
						"w": 234,
						"h": 212
					},
					"frame": {
						"x": 714,
						"y": 2908,
						"w": 234,
						"h": 212
					}
				},
				{
					"filename": "star2",
					"rotated": false,
					"trimmed": true,
					"sourceSize": {
						"w": 583,
						"h": 570
					},
					"spriteSourceSize": {
						"x": 200,
						"y": 192,
						"w": 183,
						"h": 147
					},
					"frame": {
						"x": 1,
						"y": 2999,
						"w": 183,
						"h": 147
					}
				},
				{
					"filename": "star1",
					"rotated": false,
					"trimmed": true,
					"sourceSize": {
						"w": 583,
						"h": 570
					},
					"spriteSourceSize": {
						"x": 252,
						"y": 192,
						"w": 22,
						"h": 22
					},
					"frame": {
						"x": 848,
						"y": 2549,
						"w": 22,
						"h": 22
					}
				}
			]
		}
	],
	"meta": {
		"app": "https://www.codeandweb.com/texturepacker",
		"version": "3.0",
		"smartupdate": "$TexturePacker:SmartUpdate:7f6b13bf30cd6e620024acdc9815a590:7849c5302a0f74aecc179d3e10cd8a61:8adbab821a9290c16d7773c568335da2$"
	}
}
