{
	"frames": {
		"back_arrow.png": {
			"frame": {
				"x": 1,
				"y": 1,
				"w": 46,
				"h": 79
			},
			"rotated": false,
			"trimmed": false,
			"spriteSourceSize": {
				"x": 0,
				"y": 0,
				"w": 46,
				"h": 79
			},
			"sourceSize": {
				"w": 46,
				"h": 79
			}
		},
		"bg.png": {
			"frame": {
				"x": 49,
				"y": 1,
				"w": 930,
				"h": 937
			},
			"rotated": false,
			"trimmed": false,
			"spriteSourceSize": {
				"x": 0,
				"y": 0,
				"w": 930,
				"h": 937
			},
			"sourceSize": {
				"w": 930,
				"h": 937
			}
		},
		"des_bg.png": {
			"frame": {
				"x": 981,
				"y": 1,
				"w": 73,
				"h": 68
			},
			"rotated": false,
			"trimmed": false,
			"spriteSourceSize": {
				"x": 0,
				"y": 0,
				"w": 73,
				"h": 68
			},
			"sourceSize": {
				"w": 73,
				"h": 68
			}
		},
		"ghost.png": {
			"frame": {
				"x": 1,
				"y": 940,
				"w": 75,
				"h": 109
			},
			"rotated": false,
			"trimmed": false,
			"spriteSourceSize": {
				"x": 0,
				"y": 0,
				"w": 75,
				"h": 109
			},
			"sourceSize": {
				"w": 75,
				"h": 109
			}
		},
		"grid_bg.png": {
			"frame": {
				"x": 1056,
				"y": 1,
				"w": 168,
				"h": 168
			},
			"rotated": false,
			"trimmed": false,
			"spriteSourceSize": {
				"x": 0,
				"y": 0,
				"w": 168,
				"h": 168
			},
			"sourceSize": {
				"w": 168,
				"h": 168
			}
		},
		"grid_choose.png": {
			"frame": {
				"x": 981,
				"y": 171,
				"w": 180,
				"h": 180
			},
			"rotated": false,
			"trimmed": false,
			"spriteSourceSize": {
				"x": 0,
				"y": 0,
				"w": 180,
				"h": 180
			},
			"sourceSize": {
				"w": 180,
				"h": 180
			}
		},
		"prop_bg.png": {
			"frame": {
				"x": 981,
				"y": 353,
				"w": 148,
				"h": 148
			},
			"rotated": false,
			"trimmed": false,
			"spriteSourceSize": {
				"x": 0,
				"y": 0,
				"w": 148,
				"h": 148
			},
			"sourceSize": {
				"w": 148,
				"h": 148
			}
		},
		"seach_bg.png": {
			"frame": {
				"x": 78,
				"y": 940,
				"w": 434,
				"h": 97
			},
			"rotated": false,
			"trimmed": false,
			"spriteSourceSize": {
				"x": 0,
				"y": 0,
				"w": 434,
				"h": 97
			},
			"sourceSize": {
				"w": 434,
				"h": 97
			}
		},
		"seach_down.png": {
			"frame": {
				"x": 1163,
				"y": 171,
				"w": 61,
				"h": 65
			},
			"rotated": false,
			"trimmed": false,
			"spriteSourceSize": {
				"x": 0,
				"y": 0,
				"w": 61,
				"h": 65
			},
			"sourceSize": {
				"w": 61,
				"h": 65
			}
		},
		"seach_normal.png": {
			"frame": {
				"x": 1131,
				"y": 353,
				"w": 67,
				"h": 71
			},
			"rotated": false,
			"trimmed": false,
			"spriteSourceSize": {
				"x": 0,
				"y": 0,
				"w": 67,
				"h": 71
			},
			"sourceSize": {
				"w": 67,
				"h": 71
			}
		},
		"tab_down.png": {
			"frame": {
				"x": 514,
				"y": 940,
				"w": 312,
				"h": 113
			},
			"rotated": false,
			"trimmed": false,
			"spriteSourceSize": {
				"x": 0,
				"y": 0,
				"w": 312,
				"h": 113
			},
			"sourceSize": {
				"w": 312,
				"h": 113
			}
		},
		"tab_normal.png": {
			"frame": {
				"x": 981,
				"y": 503,
				"w": 202,
				"h": 91
			},
			"rotated": false,
			"trimmed": false,
			"spriteSourceSize": {
				"x": 0,
				"y": 0,
				"w": 202,
				"h": 91
			},
			"sourceSize": {
				"w": 202,
				"h": 91
			}
		},
		"yellow_btn_down.png": {
			"frame": {
				"x": 981,
				"y": 596,
				"w": 98,
				"h": 95
			},
			"rotated": false,
			"trimmed": false,
			"spriteSourceSize": {
				"x": 0,
				"y": 0,
				"w": 98,
				"h": 95
			},
			"sourceSize": {
				"w": 98,
				"h": 95
			}
		},
		"yellow_btn_normal.png": {
			"frame": {
				"x": 1081,
				"y": 596,
				"w": 98,
				"h": 95
			},
			"rotated": false,
			"trimmed": false,
			"spriteSourceSize": {
				"x": 0,
				"y": 0,
				"w": 98,
				"h": 95
			},
			"sourceSize": {
				"w": 98,
				"h": 95
			}
		},
		"yellow_btn_over.png": {
			"frame": {
				"x": 981,
				"y": 693,
				"w": 98,
				"h": 95
			},
			"rotated": false,
			"trimmed": false,
			"spriteSourceSize": {
				"x": 0,
				"y": 0,
				"w": 98,
				"h": 95
			},
			"sourceSize": {
				"w": 98,
				"h": 95
			}
		}
	},
	"meta": {
		"app": "http://www.codeandweb.com/texturepacker",
		"version": "1.0",
		"image": "spritesheet.png",
		"format": "RGBA8888",
		"size": {
			"w": 1225,
			"h": 1054
		},
		"scale": "1"
	}
}